tweedledum/__init__.py
tweedledum/_tweedledum.cp36-win32.pyd
tweedledum/bool_function_compiler/__init__.py
tweedledum/bool_function_compiler/bitvec.py
tweedledum/bool_function_compiler/bool_function.py
tweedledum/bool_function_compiler/expression_parser.py
tweedledum/bool_function_compiler/function_parser.py
tweedledum/classical/__init__.py
tweedledum/ir/__init__.py
tweedledum/operators/__init__.py
tweedledum/passes/__init__.py
tweedledum/qiskit/__init__.py
tweedledum/qiskit/converters.py
tweedledum/qiskit/passes/__init__.py
tweedledum/qiskit/passes/mapping.py
tweedledum/qiskit/passes/decomposition/__init__.py
tweedledum/qiskit/passes/decomposition/barenco_decomp.py
tweedledum/qiskit/passes/optimization/__init__.py
tweedledum/qiskit/passes/optimization/gate_cancellation.py
tweedledum/qiskit/passes/optimization/linear_resynth.py
tweedledum/qiskit/passes/optimization/phase_folding.py
tweedledum/qiskit/passes/optimization/steiner_resynth.py
tweedledum/synthesis/__init__.py
tweedledum/target/__init__.py
tweedledum/utils/__init__.py
tweedledum-1.1.0.dist-info/LICENSE
tweedledum-1.1.0.dist-info/METADATA
tweedledum-1.1.0.dist-info/WHEEL
tweedledum-1.1.0.dist-info/top_level.txt
tweedledum-1.1.0.dist-info/RECORD
